CHANGES.rst
CONTRIBUTORS.rst
MANIFEST.in
README.rst
setup.cfg
setup.py
docs/LICENSE.GPL
docs/LICENSE.txt
docs/MSN UCP Feeds Guide v3.pdf
src/collective/__init__.py
src/collective.syndication.egg-info/PKG-INFO
src/collective.syndication.egg-info/SOURCES.txt
src/collective.syndication.egg-info/dependency_links.txt
src/collective.syndication.egg-info/entry_points.txt
src/collective.syndication.egg-info/namespace_packages.txt
src/collective.syndication.egg-info/not-zip-safe
src/collective.syndication.egg-info/requires.txt
src/collective.syndication.egg-info/top_level.txt
src/collective/syndication/__init__.py
src/collective/syndication/adapters.py
src/collective/syndication/config.py
src/collective/syndication/configure.zcml
src/collective/syndication/controlpanel.py
src/collective/syndication/events.py
src/collective/syndication/interfaces.py
src/collective/syndication/layer.py
src/collective/syndication/profiles.zcml
src/collective/syndication/settings.py
src/collective/syndication/setuphandlers.py
src/collective/syndication/testing.py
src/collective/syndication/tool.py
src/collective/syndication/utils.py
src/collective/syndication/views.py
src/collective/syndication/vocabularies.py
src/collective/syndication/locales/collective.syndication.pot
src/collective/syndication/locales/es/LC_MESSAGES/collective.syndication.mo
src/collective/syndication/locales/es/LC_MESSAGES/collective.syndication.po
src/collective/syndication/profiles/default/actions.xml
src/collective/syndication/profiles/default/browserlayer.xml
src/collective/syndication/profiles/default/controlpanel.xml
src/collective/syndication/profiles/default/metadata.xml
src/collective/syndication/profiles/default/registry.xml
src/collective/syndication/profiles/uninstall/actions.xml
src/collective/syndication/profiles/uninstall/browserlayer.xml
src/collective/syndication/profiles/uninstall/controlpanel.xml
src/collective/syndication/profiles/uninstall/registry.xml
src/collective/syndication/static/16px-Feed-icon.svg.png
src/collective/syndication/templates/RSS.pt
src/collective/syndication/templates/atom.xml.pt
src/collective/syndication/templates/content_core.pt
src/collective/syndication/templates/itunes.xml.pt
src/collective/syndication/templates/newsml.xml.pt
src/collective/syndication/templates/rss.xml.pt
src/collective/syndication/templates/search-rss.pt
src/collective/syndication/tests/__init__.py
