Metadata-Version: 1.1
Name: collective.syndication
Version: 1.0b3
Summary: Improved syndication for Plone sites providing Atom, iTunes, NewsML 1, RSS 1.0 and RSS 2.0 feeds.
Home-page: http://github.com/collective/collective.syndication
Author: Nathan Van Gheem
Author-email: UNKNOWN
License: UNKNOWN
Keywords: plone atom itunes rss syndication newsml rdf
Platform: UNKNOWN
Classifier: Development Status :: 4 - Beta
Classifier: Environment :: Web Environment
Classifier: Framework :: Plone :: 4.1
Classifier: Framework :: Plone :: 4.2
Classifier: Framework :: Plone
Classifier: Intended Audience :: End Users/Desktop
Classifier: Intended Audience :: System Administrators
Classifier: License :: OSI Approved :: GNU General Public License v2 (GPLv2)
Classifier: Operating System :: OS Independent
Classifier: Programming Language :: Python :: 2.6
Classifier: Programming Language :: Python :: 2.7
Classifier: Programming Language :: Python
Classifier: Topic :: Office/Business :: News/Diary
Classifier: Topic :: Software Development :: Libraries :: Python Modules
